LICENSE
MANIFEST.in
README.rst
requirements.txt
setup.py
facebookbot/__about__.py
facebookbot/__init__.py
facebookbot/api.py
facebookbot/exceptions.py
facebookbot/http_client.py
facebookbot/utils.py
facebookbot/webhook.py
facebookbot/models/__init__.py
facebookbot/models/actions.py
facebookbot/models/base.py
facebookbot/models/error.py
facebookbot/models/events.py
facebookbot/models/messages.py
facebookbot/models/obj.py
facebookbot/models/payload.py
facebookbot/models/persistent_menu.py
facebookbot/models/quick_reply.py
facebookbot/models/responses.py
facebookbot/models/send_messages.py
facebookbot/models/template.py
python_messengerbot_sdk.egg-info/PKG-INFO
python_messengerbot_sdk.egg-info/SOURCES.txt
python_messengerbot_sdk.egg-info/dependency_links.txt
python_messengerbot_sdk.egg-info/requires.txt
python_messengerbot_sdk.egg-info/top_level.txt